texture/__init__.py
texture/database/__init__.py
texture/database/connection.py
texture/database/preprocess.py
texture/frontend/assets/abap-ad6e811d.js
texture/frontend/assets/apex-992ba105.js
texture/frontend/assets/azcli-2ae42e71.js
texture/frontend/assets/bat-638cac0f.js
texture/frontend/assets/bicep-389290ac.js
texture/frontend/assets/cameligo-e2b87a47.js
texture/frontend/assets/clojure-9f651a27.js
texture/frontend/assets/codicon-a3faa755.ttf
texture/frontend/assets/coffee-4e075114.js
texture/frontend/assets/cpp-8ffe77ae.js
texture/frontend/assets/csharp-0b267c6b.js
texture/frontend/assets/csp-c23415e1.js
texture/frontend/assets/css-c62f5578.js
texture/frontend/assets/css.worker-68e7a658.js
texture/frontend/assets/cssMode-b6e9fa38.js
texture/frontend/assets/cypher-16871f29.js
texture/frontend/assets/dart-20618e99.js
texture/frontend/assets/dockerfile-13942c6d.js
texture/frontend/assets/ecl-82a13cc7.js
texture/frontend/assets/editor.worker-01431e3b.js
texture/frontend/assets/elixir-941d33da.js
texture/frontend/assets/flow9-82e25a0d.js
texture/frontend/assets/freemarker2-c28c05d8.js
texture/frontend/assets/fsharp-930eb6d7.js
texture/frontend/assets/go-ace823b2.js
texture/frontend/assets/graphql-9395e6dd.js
texture/frontend/assets/handlebars-a22e4909.js
texture/frontend/assets/hcl-4160620f.js
texture/frontend/assets/html-9de520b2.js
texture/frontend/assets/html.worker-507844cb.js
texture/frontend/assets/htmlMode-0c64ac02.js
texture/frontend/assets/index-4f616818.js
texture/frontend/assets/index-842cb006.css
texture/frontend/assets/ini-1cc2fa96.js
texture/frontend/assets/java-fe979474.js
texture/frontend/assets/javascript-079de301.js
texture/frontend/assets/json.worker-d3a373c5.js
texture/frontend/assets/jsonMode-79736c0a.js
texture/frontend/assets/julia-1a2d9387.js
texture/frontend/assets/kotlin-45b3a4f3.js
texture/frontend/assets/less-a184ed1c.js
texture/frontend/assets/lexon-ebf376fd.js
texture/frontend/assets/liquid-dc5fe66f.js
texture_viz-0.0.11.dist-info/LICENSE.md
texture_viz-0.0.11.dist-info/METADATA
texture_viz-0.0.11.dist-info/WHEEL
texture_viz-0.0.11.dist-info/entry_points.txt
texture_viz-0.0.11.dist-info/RECORD
