Metadata-Version: 2.3
Name: texture-viz
Version: 0.0.11
Summary: Process and profile text datasets interactively
Keywords: text,nlp,data profiling,llm
Author: Will Epperson
Author-email: willepp@live.com
Requires-Python: >=3.10
Classifier: Programming Language :: Python :: 3
Classifier: Programming Language :: Python :: 3.10
Classifier: Programming Language :: Python :: 3.11
Classifier: Programming Language :: Python :: 3.12
Classifier: Programming Language :: Python :: 3.13
Provides-Extra: extra
Requires-Dist: anywidget (>=0.9.13,<0.10.0)
Requires-Dist: duckdb (==1.1.3)
Requires-Dist: fastapi (>=0.115.7,<0.116.0)
Requires-Dist: lancedb (>=0.18.0,<0.19.0)
Requires-Dist: multiprocess (>=0.70.17,<0.71.0)
Requires-Dist: nltk (>=3.8.1) ; extra == "extra"
Requires-Dist: numpy (>=2.2.2,<3.0.0)
Requires-Dist: openai (>=1.60.2,<2.0.0)
Requires-Dist: orjson (>=3.10.15,<4.0.0)
Requires-Dist: pandas (>=2.2.3,<3.0.0)
Requires-Dist: pyarrow (>=19.0.0,<20.0.0)
Requires-Dist: pydantic (>=2.10.6,<3.0.0)
Requires-Dist: sentence-transformers (>=2.2.2) ; extra == "extra"
Requires-Dist: tiktoken (>=0.8.0,<0.9.0)
Requires-Dist: torch (>=2.1.1) ; extra == "extra"
Requires-Dist: umap-learn (>=0.5.5) ; extra == "extra"
Requires-Dist: uvicorn[standard] (>=0.34.0,<0.35.0)
Project-URL: Homepage, https://github.com/cmudig/Texture
Project-URL: Repository, https://github.com/cmudig/Texture
